{
  "_index": ".kibana",
  "_type": "visualization",
  "_id": "Device-Ids",
  "_score": 1.0,
  "_source": {
    "title": "Device Ids",
    "visState": "{\"title\":\"Device Ids\",\"type\":\"table\",\"params\":{\"perPage\":10,\"showPartialRows\":false,\"showMeticsAtAllLevels\":false,\"sort\":{\"columnIndex\":null,\"direction\":null},\"showTotal\":false,\"totalFunc\":\"sum\",\"type\":\"table\"},\"aggs\":[{\"id\":\"1\",\"enabled\":true,\"type\":\"cardinality\",\"schema\":\"metric\",\"params\":{\"field\":\"mac_address.keyword\",\"customLabel\":\"distinct devices\"}},{\"id\":\"2\",\"enabled\":true,\"type\":\"terms\",\"schema\":\"bucket\",\"params\":{\"field\":\"device_id.keyword\",\"size\":20,\"order\":\"desc\",\"orderBy\":\"1\",\"customLabel\":\"Device ID\"}},{\"id\":\"3\",\"enabled\":true,\"type\":\"count\",\"schema\":\"metric\",\"params\":{\"customLabel\":\"total detection\"}}],\"listeners\":{}}",
    "uiStateJSON": "{\"vis\":{\"params\":{\"sort\":{\"columnIndex\":null,\"direction\":null}}}}",
    "description": "",
    "version": 1,
    "kibanaSavedObjectMeta": {
      "searchSourceJSON": "{\"index\":\"logstash-*\",\"query\":{\"query_string\":{\"query\":\"mac_address:*\",\"analyze_wildcard\":true}},\"filter\":[]}"
    }
  }
}