{
  "_index": ".kibana",
  "_type": "visualization",
  "_id": "AC:86:74:74:D5:70-UMac",
  "_score": 1.0,
  "_source": {
    "title": "AC:86:74:74:D5:70-UMac",
    "visState": "{\"title\":\"AC:86:74:74:D5:70-UMac\",\"type\":\"line\",\"params\":{\"shareYAxis\":true,\"addTooltip\":true,\"addLegend\":true,\"legendPosition\":\"right\",\"showCircles\":true,\"smoothLines\":false,\"interpolate\":\"linear\",\"scale\":\"linear\",\"drawLinesBetweenPoints\":true,\"radiusRatio\":9,\"times\":[],\"addTimeMarker\":false,\"defaultYExtents\":false,\"setYExtents\":false,\"yAxis\":{}},\"aggs\":[{\"id\":\"1\",\"enabled\":true,\"type\":\"cardinality\",\"schema\":\"metric\",\"params\":{\"field\":\"mac_address.keyword\"}},{\"id\":\"2\",\"enabled\":true,\"type\":\"date_histogram\",\"schema\":\"segment\",\"params\":{\"field\":\"@timestamp\",\"interval\":\"h\",\"customInterval\":\"2h\",\"min_doc_count\":1,\"extended_bounds\":{},\"customLabel\":\"AC:86:74:74:D5:70-umac\"}},{\"id\":\"3\",\"enabled\":true,\"type\":\"filters\",\"schema\":\"group\",\"params\":{\"filters\":[{\"input\":{\"query\":{\"query_string\":{\"query\":\"\\\"AC:86:74:74:D5:70\\\"\",\"analyze_wildcard\":true}}},\"label\":\"\"}]}}],\"listeners\":{}}",
    "uiStateJSON": "{}",
    "description": "",
    "version": 1,
    "kibanaSavedObjectMeta": {
      "searchSourceJSON": "{\"index\":\"logstash-*\",\"query\":{\"query_string\":{\"query\":\"*\",\"analyze_wildcard\":true}},\"filter\":[]}"
    }
  }
}